fPrimo/__init__.py
fPrimo-1.0.dist-info/LICENSE
fPrimo-1.0.dist-info/METADATA
fPrimo-1.0.dist-info/WHEEL
fPrimo-1.0.dist-info/top_level.txt
fPrimo-1.0.dist-info/RECORD
