Metadata-Version: 2.1
Name: fPrimo
Version: 1.0
Summary: A tool to list and identify prime numbers.
Home-page: UNKNOWN
Author: Marcelo Carahyba
Author-email: marcelo.carahyba@gmail.com
License: GNU GPLv3
Keywords: prime math operations
Platform: UNKNOWN
Classifier: Development Status :: 5 - Production/Stable
Classifier: Intended Audience :: Developers
Classifier: Topic :: Utilities
Classifier: License :: OSI Approved :: GNU General Public License v3 (GPLv3)
Classifier: Programming Language :: Python :: 3
Classifier: Operating System :: OS Independent
License-File: LICENSE
